<metadata>
  <idinfo>
    <citation>
      <citeinfo>
        <origin>Universities Space Research Association, Inc., and the Goddard Space Flight Center, NASA</origin>
        <pubdate>19970114</pubdate>
        <title>The Variability of Wintertime Precipitation in the Region of California</title>
      </citeinfo>
    </citation>
    <descript>
      <abstract>Rotated principal component (RPC) analysis, subject to the varimax
     criterion and including area weighting, is applied to a 58-yr record (1931ﾖ88)
     of monthly- and seasonal-mean Climatic Division precipitation anomalies for
     the contiguous United States to document wintertime precipitation variability
     in the region of California. Rotated principal components (time series) derived
     from this analysis are related to anomalies of seasonal-mean global sea
     surface temperature, and monthly mean Northern Hemisphere 500-hPa
     geopotential height and sea level pressure (SLP).

       Wintertime seasonal-mean precipitation in California is captured by two
     RPCs. The first RPC documents coherent precipitation anomalies centered in
     northern California, Oregon, southern Idaho, and eastern Washington, and
     explains the largest portion of area-averaged variance of any of the patterns in
     the decomposition. A second RPC captures coherent precipitation variability
     in the south coast and southeast desert regions of California, southern
     Nevada, southern Utah, and northern Arizona. Fluctuations in the first RPC
     correlate poorly with Pacific Ocean SST anomalies. However, wet winters in
     the region of the second RPC correlate modestly with simultaneous cool
     western subtropical Pacific Ocean SST anomalies and weakly with warm
     SST anomalies over a broad region of the central and eastern tropical Pacific.
     The spatial scale of the tropical SST correlation and the prominent
     multidecadal timescale signal of the RPC are consistent with ENSO
     fluctuations on this timescale influencing southern California precipitation.

       Consistent with the results of earlier studies, significant correlation are
     found between California wintertime monthly mean precipitation variability
     and regional 500-hPa geopotential height and SLP anomalies. Linear
     regression analysis is used to construct estimates of the total 500-hPa
     geopotential height and SLP fields (Climatology plus anomaly) that are
     representative of the extreme wet and dry California winter months; these are
     then compared with the observed conditions in the individual extreme months.
     Several different flow patterns appear capable of producing anomalously
     large monthly precipitation totals in California.</abstract>
      <purpose>To show the variability of Wintertime Precipitation in the Region of California</purpose>
    </descript>
    <timeperd>
      <timeinfo>
        <rngdates>
          <begdate>19970114</begdate>
          <enddate />
        </rngdates>
      </timeinfo>
      <current>Publication Date</current>
    </timeperd>
    <status>
      <progress>Complete</progress>
      <update>None Planned</update>
    </status>
    <spdom>
      <bounding>
        <westbc>178</westbc>
        <eastbc>-168</eastbc>
        <northbc>67.5</northbc>
        <southbc>52</southbc>
      </bounding>
    </spdom>
    <keywords>
      <theme>
        <themekt>North Pacific Ecosystem Metadatabase</themekt>
        <themekey>Meteorology</themekey>
      </theme>
      <theme>
        <themekt>Other</themekt>
        <themekey>Bering Sea</themekey>
        <themekey>Alaska</themekey>
        <themekey>North Pacific Ocean</themekey>
      </theme>
    </keywords>
    <accconst>Check with Contributor</accconst>
    <useconst>Check with Contributor</useconst>
    <ptcontac>
      <cntinfo>
        <cntperp>
          <cntper>Mitchell, Todd P.</cntper>
        </cntperp>
        <cntaddr>
          <addrtype>Mailing and Physical Address</addrtype>
          <address>NASA/Goddard Space Flight Center</address>
          <city>Greenbelt</city>
          <state>MD</state>
          <postal>20771</postal>
          <country>USA</country>
        </cntaddr>
        <cntvoice />
        <cntfax />
        <cntemail />
      </cntinfo>
    </ptcontac>
  </idinfo>
  <distinfo>
    <distrib>
      <cntinfo>
        <cntperp>
          <cntper>Mitchell, Todd P.</cntper>
        </cntperp>
        <cntaddr>
          <addrtype>Mailing and Physical Address</addrtype>
          <address>NASA/Goddard Space Flight Center</address>
          <city>Greenbelt</city>
          <state>MD</state>
          <postal>20771</postal>
          <country>USA</country>
        </cntaddr>
        <cntvoice />
        <cntfax />
        <cntemail />
      </cntinfo>
    </distrib>
    <distliab>While every effort has been made to ensure that these data are accurate and reliable within the limits of the current state of the art, NOAA cannot assume liability for any damages caused by any errors or omissions in the data, nor as a result of the failure of the data to function on a particular system. NOAA makes no warranty, expressed or implied, nor does the fact of distribution constitute such a warranty.</distliab>
  </distinfo>
  <metainfo>
    <metd>19990205</metd>
    <metc>
      <cntinfo>
        <cntperp>
          <cntper>Kimberly Bahl</cntper>
        </cntperp>
        <cntaddr>
          <addrtype>Mailing and Physical Address</addrtype>
          <address>NOAA / AFSC / PMEL, 7600 Sand Point Way N.E.</address>
          <city>Seattle</city>
          <state>WA</state>
          <postal>98115</postal>
          <country>USA</country>
        </cntaddr>
        <cntvoice>206-526-4314</cntvoice>
        <cntfax>206-526-6485</cntfax>
        <cntemail>kimberly.bahl@noaa.gov</cntemail>
      </cntinfo>
    </metc>
    <metstdn>Content Standards for Digital Geospatial Metadata</metstdn>
    <metstdv>FGDC-STD-001-1998</metstdv>
    <metac>Check with Contributor</metac>
    <metuc>Check with Contributor</metuc>
  </metainfo>
</metadata>
