<metadata>
  <idinfo>
    <citation>
      <citeinfo>
        <origin>North Pacific Marine Science Organization (PICES)</origin>
        <pubdate>1998</pubdate>
        <title>PICES Scientific Report No. 8 (1998) - Multilingual Nomenclature of Place and Oceanographic Names in the Region of the Okhotsk Sea : Report of the Physical Oceanography and Climate Committee : Reprint from a MIRC Science Report / edited by Yutaka Nagata and Vyacheslav B. Lobanov</title>
      </citeinfo>
    </citation>
    <descript>
      <abstract>The multilingual problem of place and oceanographic names often occurs in the region of the Okhotsk Sea, especially in Souther Sakhalin (Minami Karafuto) and in the Kuril Islands (Chishima Islands) area, due to historical reasons.  This report provides a list of nomenclature of bays, straits, currents in the Okhotsk Sea region in all the languages of PICES member countries.
   [ LC Call No. GC781 .P535 no.8.  ISBN 0969842082 ]</abstract>
      <purpose>To compile multilingual nomenclature of bays, straits, currents in the Okhotsk Sea region.</purpose>
    </descript>
    <timeperd>
      <timeinfo />
      <current>Publication Date</current>
    </timeperd>
    <status>
      <progress>Complete</progress>
      <update>None Planned</update>
    </status>
    <spdom>
      <bounding>
        <westbc>137</westbc>
        <eastbc>164</eastbc>
        <northbc>62</northbc>
        <southbc>43</southbc>
      </bounding>
    </spdom>
    <keywords>
      <theme>
        <themekt>Other</themekt>
        <themekey>Nomenclature</themekey>
        <themekey>Sea of Okhotsk</themekey>
        <themekey>North Pacific Ocean</themekey>
      </theme>
    </keywords>
    <accconst>None</accconst>
    <useconst>Acknowledgement of source publication required.</useconst>
    <ptcontac>
      <cntinfo>
        <cntperp>
          <cntper>North Pacific Marine Science Organization</cntper>
        </cntperp>
        <cntaddr>
          <addrtype>Mailing Address</addrtype>
          <address>c/o Institute of Ocean Sciences
P.O. Box 6000</address>
          <city>Sidney</city>
          <state>BC</state>
          <postal>V8L 4B2</postal>
          <country>Canada</country>
        </cntaddr>
        <cntvoice>250-363-6366</cntvoice>
        <cntfax>250-363-6827</cntfax>
        <cntemail>secretariat@pices.int</cntemail>
      </cntinfo>
    </ptcontac>
  </idinfo>
  <distinfo>
    <distrib>
      <cntinfo>
        <cntperp>
          <cntper>North Pacific Marine Science Organization</cntper>
        </cntperp>
        <cntaddr>
          <addrtype>Mailing Address</addrtype>
          <address>c/o Institute of Ocean Sciences
P.O. Box 6000</address>
          <city>Sidney</city>
          <state>BC</state>
          <postal>V8L 4B2</postal>
          <country>Canada</country>
        </cntaddr>
        <cntvoice>250-363-6366</cntvoice>
        <cntfax>250-363-6827</cntfax>
        <cntemail>secretariat@pices.int</cntemail>
      </cntinfo>
    </distrib>
    <distliab>While every effort has been made to ensure that these data are accurate and reliable within the limits of the current state of the art, NOAA cannot assume liability for any damages caused by any errors or omissions in the data, nor as a result of the failure of the data to function on a particular system. NOAA makes no warranty, expressed or implied, nor does the fact of distribution constitute such a warranty.</distliab>
  </distinfo>
  <metainfo>
    <metd>20040601</metd>
    <metc>
      <cntinfo>
        <cntperp>
          <cntper>Kimberly Bahl</cntper>
        </cntperp>
        <cntaddr>
          <addrtype>Mailing and Physical Address</addrtype>
          <address>NOAA / AFSC / PMEL, 7600 Sand Point Way N.E.</address>
          <city>Seattle</city>
          <state>WA</state>
          <postal>98115</postal>
          <country>USA</country>
        </cntaddr>
        <cntvoice>206-526-4314</cntvoice>
        <cntfax>206-526-6485</cntfax>
        <cntemail>kimberly.bahl@noaa.gov</cntemail>
      </cntinfo>
    </metc>
    <metstdn>Content Standards for Digital Geospatial Metadata</metstdn>
    <metstdv>FGDC-STD-001-1998</metstdv>
    <metac>None</metac>
    <metuc>Acknowledgement of source publication required.</metuc>
  </metainfo>
</metadata>
