<metadata>
  <idinfo>
    <citation>
      <citeinfo>
        <origin>National Snow and Ice Data Center (NSIDC)</origin>
        <pubdate>Unknown</pubdate>
        <title>ETOP05 Elevation Data for Areas Greater than 50 Degrees North</title>
      </citeinfo>
    </citation>
    <descript>
      <abstract>The data in the provided files are the ETOPO5 gridded elevation data for the Earth, subsetted for the Arctic area above 50 degrees North.  The data were provided to NSIDC for this project by Michael S. Loughridge and George F. Sharman at the National Geophysical Data Center (NGDC), Boulder, Colorado.  

For further information about the ETOPO5 data set, and for access to the full data set and other subsetting and data formatting options, please see: http://www.ngdc.noaa.gov/mgg/global/seltopo.html.  

The elevation data in the files whole_arctic.bin, east_arctic.bin, and west_arctic.bin are 2-byte, signed, big-endian integer values representing meters above sea level (i.e. negative values are below sea level).  They are 1-band image files with no header.  

The data are also available as ArcInfo (vs. 8.0.1) grids, which have been tarred as directories to include the requisite info directory, or as ASCII files in row-major order (with ArcInfo headers, which may be stripped if unnecessary for your needs).</abstract>
      <purpose>To archive gridded elevation data.</purpose>
    </descript>
    <timeperd>
      <timeinfo />
      <current>Ground Condition</current>
    </timeperd>
    <status>
      <progress>Complete</progress>
      <update>Unknown</update>
    </status>
    <spdom>
      <bounding>
        <westbc>-180</westbc>
        <eastbc>180</eastbc>
        <northbc>90</northbc>
        <southbc>50</southbc>
      </bounding>
    </spdom>
    <keywords>
      <theme>
        <themekt>Other</themekt>
        <themekey>North Pacific Ocean</themekey>
      </theme>
    </keywords>
    <accconst>None</accconst>
    <useconst>Contact Source.</useconst>
    <ptcontac>
      <cntinfo>
        <cntperp>
          <cntper>NSIDC User Services</cntper>
        </cntperp>
        <cntaddr>
          <addrtype>Mailing and Physical Address</addrtype>
          <address>CIRES, 449 UCB</address>
          <city>Boulder</city>
          <state>CO</state>
          <postal>80309-0449</postal>
          <country>USA</country>
        </cntaddr>
        <cntvoice>303-492-6199</cntvoice>
        <cntfax>303-492-2468</cntfax>
        <cntemail>nsidc@nsidc.org</cntemail>
      </cntinfo>
    </ptcontac>
  </idinfo>
  <distinfo>
    <distrib>
      <cntinfo>
        <cntperp>
          <cntper>NSIDC User Services</cntper>
        </cntperp>
        <cntaddr>
          <addrtype>Mailing and Physical Address</addrtype>
          <address>CIRES, 449 UCB</address>
          <city>Boulder</city>
          <state>CO</state>
          <postal>80309-0449</postal>
          <country>USA</country>
        </cntaddr>
        <cntvoice>303-492-6199</cntvoice>
        <cntfax>303-492-2468</cntfax>
        <cntemail>nsidc@nsidc.org</cntemail>
      </cntinfo>
    </distrib>
    <distliab>While every effort has been made to ensure that these data are accurate and reliable within the limits of the current state of the art, NOAA cannot assume liability for any damages caused by any errors or omissions in the data, nor as a result of the failure of the data to function on a particular system. NOAA makes no warranty, expressed or implied, nor does the fact of distribution constitute such a warranty.</distliab>
  </distinfo>
  <metainfo>
    <metd>20040426</metd>
    <metc>
      <cntinfo>
        <cntperp>
          <cntper>Kimberly Bahl</cntper>
        </cntperp>
        <cntaddr>
          <addrtype>Mailing and Physical Address</addrtype>
          <address>NOAA / AFSC / PMEL, 7600 Sand Point Way N.E.</address>
          <city>Seattle</city>
          <state>WA</state>
          <postal>98115</postal>
          <country>USA</country>
        </cntaddr>
        <cntvoice>206-526-4314</cntvoice>
        <cntfax>206-526-6485</cntfax>
        <cntemail>kimberly.bahl@noaa.gov</cntemail>
      </cntinfo>
    </metc>
    <metstdn>Content Standards for Digital Geospatial Metadata</metstdn>
    <metstdv>FGDC-STD-001-1998</metstdv>
    <metac>None</metac>
    <metuc>Contact Source.</metuc>
  </metainfo>
</metadata>
