<metadata>
  <idinfo>
    <citation>
      <citeinfo>
        <origin>National Oceanic and Atmospheric Administration (NOAA), Office of Oceanic and Atmospheric Research (OAR), Pacific Marine Environmental Laboratory (PMEL)</origin>
        <pubdate>1997</pubdate>
        <title>Internal Deformation of the Gorda Plate Observed by Hydroacoustic Monitoring</title>
      </citeinfo>
    </citation>
    <descript>
      <abstract>On August 29, 1991, the National Oceanic and Atmospheric Administration VENTS Program began monitoring the northeast Pacific Ocean plate boundaries using
continuously recorded data from the U.S. Navyﾒs Sound Surveillance System (SOSUS) hydrophone arrays. Routine detection and location of small (2.4  M  3.5)
earthquakes revealed a NNE-SSW trending band of seismicity through the center of the Gorda Plate. The majority of the earthquakes in the band were not
detected by land-based seismic networks. This band of microearthquakes was active from the initiation of SOSUS monitoring in August 1991 through July 1992, at
a rate of ~20 events per week. Since August 1992, however, the activity has effectively ceased. Some of the microearthquakes in the band are likely aftershocks to
three large (M &gt; 6) mid Gorda Plate earthquakes that occurred 1-2 months prior to the beginning of SOSUS monitoring. The hydroacoustically detected events in
the band, however, do not occur in the proximity of the M &gt; 6 events, and the activity level increased several months afterward, suggesting the microseismicity
band represents a more general pattern of deformation within the Gorda Plate. The cessation of the midplate activity follows the occurrence of a large earthquake
sequence in the adjacent Cascadia Subduction Zone in April 1992. It is proposed that the band of microseismicity and the three large midplate events reflect an
accumulation of stress in the Gorda Plate, with the eventual termination of this pattern due to stress reduction associated with movement in the adjacent subduction
zone. Stress field modeling of the region yields results consistent with this interpretation.</abstract>
      <purpose />
    </descript>
    <timeperd>
      <timeinfo />
      <current>Publication Date</current>
    </timeperd>
    <status>
      <progress>Complete</progress>
      <update>None Planned</update>
    </status>
    <spdom>
      <bounding>
        <westbc>-127</westbc>
        <eastbc>-123.5</eastbc>
        <northbc>42</northbc>
        <southbc>40</southbc>
      </bounding>
    </spdom>
    <keywords>
      <theme>
        <themekt>Other</themekt>
        <themekey>North Pacific Ocean</themekey>
      </theme>
    </keywords>
    <accconst>Check with Contributor</accconst>
    <useconst>Check with Contributor</useconst>
    <ptcontac>
      <cntinfo>
        <cntperp>
          <cntper>Fox, Christopher G.</cntper>
        </cntperp>
        <cntaddr>
          <addrtype>Mailing and Physical Address</addrtype>
          <address>2115 SE OSU Drive</address>
          <city>Newport</city>
          <state>OR</state>
          <postal>97365</postal>
          <country>USA</country>
        </cntaddr>
        <cntvoice>541-867-0276</cntvoice>
        <cntfax />
        <cntemail>Christopher.G.Fox@noaa.gov</cntemail>
      </cntinfo>
    </ptcontac>
  </idinfo>
  <distinfo>
    <distrib>
      <cntinfo>
        <cntperp>
          <cntper>Fox, Christopher G.</cntper>
        </cntperp>
        <cntaddr>
          <addrtype>Mailing and Physical Address</addrtype>
          <address>2115 SE OSU Drive</address>
          <city>Newport</city>
          <state>OR</state>
          <postal>97365</postal>
          <country>USA</country>
        </cntaddr>
        <cntvoice>541-867-0276</cntvoice>
        <cntfax />
        <cntemail>Christopher.G.Fox@noaa.gov</cntemail>
      </cntinfo>
    </distrib>
    <distliab>While every effort has been made to ensure that these data are accurate and reliable within the limits of the current state of the art, NOAA cannot assume liability for any damages caused by any errors or omissions in the data, nor as a result of the failure of the data to function on a particular system. NOAA makes no warranty, expressed or implied, nor does the fact of distribution constitute such a warranty.</distliab>
  </distinfo>
  <metainfo>
    <metd>20010308</metd>
    <metc>
      <cntinfo>
        <cntperp>
          <cntper>Kimberly Bahl</cntper>
        </cntperp>
        <cntaddr>
          <addrtype>Mailing and Physical Address</addrtype>
          <address>NOAA / AFSC / PMEL, 7600 Sand Point Way N.E.</address>
          <city>Seattle</city>
          <state>WA</state>
          <postal>98115</postal>
          <country>USA</country>
        </cntaddr>
        <cntvoice>206-526-4314</cntvoice>
        <cntfax>206-526-6485</cntfax>
        <cntemail>kimberly.bahl@noaa.gov</cntemail>
      </cntinfo>
    </metc>
    <metstdn>Content Standards for Digital Geospatial Metadata</metstdn>
    <metstdv>FGDC-STD-001-1998</metstdv>
    <metac>Check with Contributor</metac>
    <metuc>Check with Contributor</metuc>
  </metainfo>
</metadata>
